bgc_prophet/__init__.py
bgc_prophet/main.py
bgc_prophet/command/__init__.py
bgc_prophet/command/baseCommand.py
bgc_prophet/command/classify.py
bgc_prophet/command/extract.py
bgc_prophet/command/organize.py
bgc_prophet/command/output.py
bgc_prophet/command/pipline.py
bgc_prophet/command/predict.py
bgc_prophet/command/split.py
bgc_prophet/train/__init__.py
bgc_prophet/train/batch3Linear.py
bgc_prophet/train/classifier.py
bgc_prophet/train/classifyEval.py
bgc_prophet/train/classifyTrainer.py
bgc_prophet/train/data.py
bgc_prophet/train/eval.py
bgc_prophet/train/eval_all.py
bgc_prophet/train/final_val.py
bgc_prophet/train/focal_loss.py
bgc_prophet/train/loss.py
bgc_prophet/train/lstm_model.py
bgc_prophet/train/model.py
bgc_prophet/train/trainer.py
bgc_prophet/train/trainer_focal_loss.py
bgc_prophet/train/utils.py
bgc_prophet-0.1.2.dist-info/LICENSE
bgc_prophet-0.1.2.dist-info/METADATA
bgc_prophet-0.1.2.dist-info/WHEEL
bgc_prophet-0.1.2.dist-info/entry_points.txt
bgc_prophet-0.1.2.dist-info/top_level.txt
bgc_prophet-0.1.2.dist-info/RECORD
