Metadata-Version: 2.1
Name: bgc-prophet
Version: 0.1.2
Summary: A cutting-edge deep learning approach that leverages language processing neural network to accurately identify known BGCs and extrapolate novel ones. 
Home-page: https://github.com/HUST-NingKang-Lab/BGC-Prophet
Author: HUST NingKang Lab
Author-email: laiqilong@hust.edu.cn
License: MIT
Classifier: License :: OSI Approved :: MIT License
Classifier: Programming Language :: Python
Classifier: Programming Language :: Python :: 3
Classifier: Programming Language :: Python :: 3.8
Classifier: Programming Language :: Python :: 3.9
Classifier: Programming Language :: Python :: 3.10
Classifier: Programming Language :: Python :: 3.11
Classifier: Programming Language :: Python :: Implementation :: CPython
Classifier: Programming Language :: Python :: Implementation :: PyPy
Requires-Python: >=3.6.0
License-File: LICENSE
Requires-Dist: torch
Requires-Dist: lmdb
Requires-Dist: pandas
Requires-Dist: numpy
Requires-Dist: tqdm
Requires-Dist: scikit-learn
Requires-Dist: matplotlib
Requires-Dist: fair-esm
Requires-Dist: biopython
